gls/__init__.py
gls/__version__.py
gls/address.py
gls/gls.py
gls/gls_types.py
gls/parcel.py
gls/response.py
gls/service.py
gls/settings.py
tests/__init__.py
tests/test_gls.py
mygls_rest_client-1.0.0.dist-info/LICENSE
mygls_rest_client-1.0.0.dist-info/METADATA
mygls_rest_client-1.0.0.dist-info/WHEEL
mygls_rest_client-1.0.0.dist-info/top_level.txt
mygls_rest_client-1.0.0.dist-info/zip-safe
mygls_rest_client-1.0.0.dist-info/RECORD
