Metadata-Version: 2.1
Name: mygls-rest-client
Version: 1.0.0
Summary: MyGLS REST API client
Home-page: https://github.com/adamkornafeld/mygls-python
Author: Adam Kornafeld
Author-email: adam@kornafeld.com
License: Apache Software License 2.0 (Apache-2.0)
Project-URL: Documentation, https://github.com/adamkornafeld/mygls-python/blob/main/README.md
Project-URL: Source, https://github.com/adamkornafeld/mygls-python
Keywords: gls,mygls,api,rest,package,parcel,label,print
Classifier: Programming Language :: Python :: 3
Classifier: License :: OSI Approved :: Apache Software License
Classifier: Operating System :: OS Independent
Requires-Python: >=3.8
License-File: LICENSE
Requires-Dist: pydantic (<2.0.0,>=1.10.2)
Requires-Dist: requests (<3.0.0,>=2.28.1)
Provides-Extra: dev
Requires-Dist: black (==22.10.0) ; extra == 'dev'
Requires-Dist: pylint (==2.15.8) ; extra == 'dev'
Provides-Extra: test
Requires-Dist: responses (<1.0.0,>=0.22.0) ; extra == 'test'
